{
  "version": "1.0.0",
  "description": "CARD 112",
  "groups": [
    {
      "name": "group_1",
      "displayName": "группа 1",
      "grid": {
        "column": 1,
        "row": 1
      },
      "fields": [
        {
          "type": "GROUP",
          "name": "checkbox1",
          "displayName": "Группа",
          "value": "false",
          "placeholder": "",
          "grid": {
            "column": 1,
            "row": 2
          },
          "groups": [
            {
              "name": "group_2",
              "displayName": "вложенная группа 2",
              "grid": {
                "column": 1,
                "row": 1
              },
              "fields": [
                {
                  "type": "CHECKBOX",
                  "name": "checkbox1",
                  "displayName": "чекбок 1",
                  "value": "false",
                  "placeholder": ""
                }
              ]
            },
            {
              "name": "group_3",
              "displayName": "вложенная группа 3",
              "grid": {
                "column": 1,
                "row": 2
              },
              "fields": [
                {
                  "type": "CHECKBOX",
                  "name": "checkbox1",
                  "displayName": "чекбок 1",
                  "value": "false",
                  "placeholder": ""
                }
              ]
            }
          ]
        },
        {
          "type": "CHECKBOX",
          "name": "checkbox1",
          "displayName": "чекбок 1",
          "value": "false",
          "placeholder": "",
          "grid": {
            "column": 1,
            "row": 1
          }
        }
      ]
    },
    {
      "name": "group_2",
      "displayName": "группа 2",
      "grid": {
        "column": 1,
        "row": 2
      },
      "fields": [
        {
          "type": "GROUP",
          "name": "checkbox1",
          "displayName": "чекбок 1",
          "value": "false",
          "placeholder": "",
          "grid": {
            "column": 1,
            "row": 2
          },
          "groups": [
            {
              "name": "group_2",
              "displayName": "вложенная группа 2",
              "grid": {
                "column": 1,
                "row": 1
              },
              "fields": [
                {
                  "type": "CHECKBOX",
                  "name": "checkbox1",
                  "displayName": "чекбок 1",
                  "value": "false",
                  "placeholder": ""
                }
              ]
            },
            {
              "name": "group_3",
              "displayName": "вложенная группа 3",
              "grid": {
                "column": 1,
                "row": 2
              },
              "fields": [
                {
                  "type": "CHECKBOX",
                  "name": "checkbox1",
                  "displayName": "чекбок 1",
                  "value": "false",
                  "placeholder": ""
                }
              ]
            }
          ]
        },
        {
          "type": "CHECKBOX",
          "name": "checkbox1",
          "displayName": "чекбок 1",
          "value": "false",
          "placeholder": "",
          "grid": {
            "column": 1,
            "row": 1
          }
        }
      ]
    }
  ]
}